azure/purview/workflow/__init__.py
azure/purview/workflow/_client.py
azure/purview/workflow/_configuration.py
azure/purview/workflow/_patch.py
azure/purview/workflow/_serialization.py
azure/purview/workflow/_vendor.py
azure/purview/workflow/_version.py
azure/purview/workflow/py.typed
azure/purview/workflow/aio/__init__.py
azure/purview/workflow/aio/_client.py
azure/purview/workflow/aio/_configuration.py
azure/purview/workflow/aio/_patch.py
azure/purview/workflow/aio/_vendor.py
azure/purview/workflow/aio/operations/__init__.py
azure/purview/workflow/aio/operations/_operations.py
azure/purview/workflow/aio/operations/_patch.py
azure/purview/workflow/operations/__init__.py
azure/purview/workflow/operations/_operations.py
azure/purview/workflow/operations/_patch.py
azure_purview_workflow-1.0.0b2.dist-info/LICENSE
azure_purview_workflow-1.0.0b2.dist-info/METADATA
azure_purview_workflow-1.0.0b2.dist-info/WHEEL
azure_purview_workflow-1.0.0b2.dist-info/top_level.txt
azure_purview_workflow-1.0.0b2.dist-info/RECORD
